CASpy_ReactionEquilibria/__init__.py
CASpy_ReactionEquilibria/caspy.py
caspy_reactionequilibria-0.1.6.dist-info/METADATA
caspy_reactionequilibria-0.1.6.dist-info/WHEEL
caspy_reactionequilibria-0.1.6.dist-info/licenses/LICENSE
caspy_reactionequilibria-0.1.6.dist-info/RECORD
