Metadata-Version: 2.1
Name: CASpy_ReactionEquilibria
Version: 0.1.6
Summary: CASpy package to solve reaction equilibria
Project-URL: Homepage, https://github.com/omoultosEthTuDelft/CASpy
Author-email: "H. Mert Polat" <h.m.polat@tudelft.nl>
License-File: LICENSE
Classifier: License :: OSI Approved :: MIT License
Classifier: Operating System :: OS Independent
Classifier: Programming Language :: Python :: 3
Requires-Python: >=3.7
